HoloLink/HoloLink.py
HoloLink/__init__.py
HoloLink/HLLoader/Loader.py
HoloLink/HLLoader/__init__.py
HoloLink/HLPackageManager/PackageManager.py
HoloLink/HLPackageManager/__init__.py
HoloLink/HLParsers/Parsers.py
HoloLink/HLParsers/__init__.py
HoloLink/HLParsers/ActionParser/ActionParser.py
HoloLink/HLParsers/ActionParser/__init__.py
HoloLink/HLParsers/ArgumentParser/ArgumentParser.py
HoloLink/HLParsers/ArgumentParser/__init__.py
HoloLink/HLParsers/SkillParser/SkillParser.py
HoloLink/HLParsers/SkillParser/__init__.py
HoloLink/HLParsers/ToolParser/ToolParser.py
HoloLink/HLParsers/ToolParser/__init__.py
HoloLink/HLSkillMover/SkillMover.py
HoloLink/HLSkillMover/__init__.py
HoloLink/HLUtils/Utils.py
HoloLink/HLUtils/__init__.py
hololink-0.2.2.dist-info/METADATA
hololink-0.2.2.dist-info/WHEEL
hololink-0.2.2.dist-info/top_level.txt
hololink-0.2.2.dist-info/RECORD
